profiling/__init__.py
profiling/accuracy.py
profiling/convenience.py
profiling/countplot.py
profiling/dependence.py
profiling/expectations.py
profiling/importance.py
profiling/metrics.py
profiling/shap.py
profiling/sliceloss.py
profiling/t.py
profiling/utils.py
tests/__init__.py
tests/test_countplot.py
tests/test_creation.py
tests/test_expectations.py
tests/test_importance.py
tests/test_metrics.py
tests/test_roc.py
tests/test_shap.py
tests/test_sliceloss.py
tests/test_validation_dataframe.py
taktile_profiling-1.5.15.dist-info/METADATA
taktile_profiling-1.5.15.dist-info/WHEEL
taktile_profiling-1.5.15.dist-info/top_level.txt
taktile_profiling-1.5.15.dist-info/RECORD
