Metadata-Version: 2.1
Name: taktile-profiling
Version: 1.5.15
Summary: Taktile's Profiling Module
Home-page: https://docs.taktile.com
Author: Taktile GmbH
Author-email: devops@taktile.com
Keywords: taktile-profiling
Classifier: Intended Audience :: Developers
Classifier: License :: OSI Approved :: Apache Software License
Classifier: Programming Language :: Python :: 3.7
Classifier: Programming Language :: Python :: 3.8
Classifier: Programming Language :: Python :: 3.9
Classifier: Programming Language :: Python :: 3.10
Requires-Python: >=3.7, <3.11
Requires-Dist: uvicorn ==0.14.0
Requires-Dist: fastapi ==0.65.2
Requires-Dist: pydantic ==1.8.*
Requires-Dist: requests <3.0.0,>=2.26.0
Requires-Dist: pytest ==7.1.1
Requires-Dist: pytest-json-report ==1.5.0
Requires-Dist: numpy <1.25,>=1.21.0
Requires-Dist: pandas <2,>=1.2
Requires-Dist: altair ==4.1.*
Requires-Dist: urllib3 <2
